src/__init__.py
src/auth.py
src/cli.py
src/config.py
src/main.py
src/version.py
automagik_agents-0.1.3.dist-info/LICENSE
automagik_agents-0.1.3.dist-info/METADATA
automagik_agents-0.1.3.dist-info/WHEEL
automagik_agents-0.1.3.dist-info/entry_points.txt
automagik_agents-0.1.3.dist-info/top_level.txt
automagik_agents-0.1.3.dist-info/RECORD
