Metadata-Version: 2.2
Name: automagik-agents
Version: 0.1.3
Summary: Automagik agents templates
Author-email: Cezar Vasconcelos <cezar@namastex.ai>
License: MIT
Project-URL: Homepage, https://github.com/namastexlabs/automagik-agents
Project-URL: Repository, https://github.com/namastexlabs/automagik-agents
Project-URL: Issues, https://github.com/namastexlabs/automagik-agents/issues
Keywords: ai,agents,pydantic,fastapi,notion
Classifier: Development Status :: 3 - Alpha
Classifier: Intended Audience :: Developers
Classifier: License :: OSI Approved :: MIT License
Classifier: Programming Language :: Python :: 3
Classifier: Programming Language :: Python :: 3.10
Classifier: Programming Language :: Python :: 3.11
Requires-Python: >=3.10
License-File: LICENSE
Requires-Dist: python-dotenv>=1.0.1
Requires-Dist: notion-client>=2.3.0
Requires-Dist: pydantic-ai>=0.0.24
Requires-Dist: rich>=13.9.4
Requires-Dist: logfire>=3.6.1
Requires-Dist: fastapi>=0.104.1
Requires-Dist: uvicorn>=0.24.0
Requires-Dist: pydantic-settings>=2.8.0
Requires-Dist: typer>=0.9.0
Requires-Dist: build>=1.2.2.post1
Requires-Dist: twine>=6.1.0
